werkflow_system/__init__.py
werkflow_system/system.py
werkflow_system/architecture/__init__.py
werkflow_system/architecture/types.py
werkflow_system/configuration/__init__.py
werkflow_system/configuration/configuration.py
werkflow_system/configuration/configuration_summary.py
werkflow_system/configuration/cpu.py
werkflow_system/configuration/data_amount.py
werkflow_system/configuration/drive.py
werkflow_system/configuration/drive_group.py
werkflow_system/configuration/memory.py
werkflow_system/exceptions/__init__.py
werkflow_system/exceptions/missing_volume_exception.py
werkflow_system/exceptions/unsupported_architecture_exception.py
werkflow_system/exceptions/unsupported_operating_system_exception.py
werkflow_system/operating_system/__init__.py
werkflow_system/operating_system/base.py
werkflow_system/operating_system/linux.py
werkflow_system/operating_system/mac_os.py
werkflow_system/operating_system/types.py
werkflow_system/operating_system/windows.py
werkflow_system/users/__init__.py
werkflow_system/users/users.py
werkflow_system-0.3.2.dist-info/licenses/LICENSE
werkflow_system-0.3.2.dist-info/METADATA
werkflow_system-0.3.2.dist-info/WHEEL
werkflow_system-0.3.2.dist-info/top_level.txt
werkflow_system-0.3.2.dist-info/RECORD
